tej/__init__.py
tej/__main__.py
tej/errors.py
tej/main.py
tej/submission.py
tej/utils.py
tej/remotes/default/version
tej/remotes/default/commands/delete
tej/remotes/default/commands/kill
tej/remotes/default/commands/list
tej/remotes/default/commands/new_job
tej/remotes/default/commands/setup
tej/remotes/default/commands/start
tej/remotes/default/commands/status
tej/remotes/default/commands/submit
tej/remotes/default/commands/lib/utils.sh
tej/remotes/pbs/version
tej/remotes/pbs/commands/delete
tej/remotes/pbs/commands/kill
tej/remotes/pbs/commands/list
tej/remotes/pbs/commands/new_job
tej/remotes/pbs/commands/setup
tej/remotes/pbs/commands/status
tej/remotes/pbs/commands/submit
tej/remotes/pbs/commands/lib/utils.sh
tej-0.6.dist-info/DESCRIPTION.rst
tej-0.6.dist-info/METADATA
tej-0.6.dist-info/RECORD
tej-0.6.dist-info/WHEEL
tej-0.6.dist-info/entry_points.txt
tej-0.6.dist-info/metadata.json
tej-0.6.dist-info/top_level.txt
