Metadata-Version: 2.0
Name: tej
Version: 0.6
Summary: Trivial Extensible Job-submission system
Home-page: https://github.com/VisTrails/tej
Author: Remi Rampin
Author-email: remirampin@gmail.com
License: BSD
Keywords: tej,job,submission,queue,batch,ssh,server,pbs,qsub
Platform: UNKNOWN
Classifier: Development Status :: 4 - Beta
Classifier: Environment :: Console
Classifier: Intended Audience :: Information Technology
Classifier: Intended Audience :: Science/Research
Classifier: License :: OSI Approved :: BSD License
Classifier: Programming Language :: Python :: 2
Classifier: Programming Language :: Python :: 3
Classifier: Topic :: Internet
Classifier: Topic :: Scientific/Engineering
Classifier: Topic :: System :: Distributed Computing
Classifier: Topic :: System :: Shells
Classifier: Topic :: Utilities
Requires-Dist: paramiko
Requires-Dist: rpaths
Requires-Dist: scp
